{
  "_class": "shapePath",
  "booleanOperation": -1,
  "clippingMaskMode": 0,
  "do_objectID": "49019961-5446-419E-AF93-7A196262CE50",
  "edited": true,
  "exportOptions": {
    "_class": "exportOptions",
    "exportFormats": [
    ],
    "includedLayerIds": [
    ],
    "layerOptions": 0,
    "shouldTrim": false
  },
  "frame": {
    "_class": "rect",
    "constrainProportions": false,
    "height": 5.39759036144576,
    "width": 2.203334965317298,
    "x": 14.12209983205164,
    "y": 0.4738955823292972
  },
  "hasClippingMask": false,
  "isClosed": true,
  "isFixedToViewport": false,
  "isFlippedHorizontal": false,
  "isFlippedVertical": false,
  "isLocked": false,
  "isVisible": true,
  "layerListExpandedType": 0,
  "maintainScrollPosition": false,
  "name": "Path",
  "nameIsFixed": false,
  "pointRadiusBehaviour": 1,
  "points": [
    {
      "_class": "curvePoint",
      "cornerRadius": 0,
      "curveFrom": "{0.62681159420289756, 0.23065476190476461}",
      "curveMode": 1,
      "curveTo": "{0.62681159420289756, 0.23065476190476461}",
      "hasCurveFrom": false,
      "hasCurveTo": false,
      "point": "{0.62681159420289756, 0.23065476190476461}"
    },
    {
      "_class": "curvePoint",
      "cornerRadius": 0,
      "curveFrom": "{1, 0.23065476190476461}",
      "curveMode": 1,
      "curveTo": "{1, 0.23065476190476461}",
      "hasCurveFrom": false,
      "hasCurveTo": false,
      "point": "{1, 0.23065476190476461}"
    },
    {
      "_class": "curvePoint",
      "cornerRadius": 0,
      "curveFrom": "{1, 0.34226190476191221}",
      "curveMode": 1,
      "curveTo": "{1, 0.34226190476191221}",
      "hasCurveFrom": false,
      "hasCurveTo": false,
      "point": "{1, 0.34226190476191221}"
    },
    {
      "_class": "curvePoint",
      "cornerRadius": 0,
      "curveFrom": "{0.62681159420289756, 0.34226190476191221}",
      "curveMode": 1,
      "curveTo": "{0.62681159420289756, 0.34226190476191221}",
      "hasCurveFrom": false,
      "hasCurveTo": false,
      "point": "{0.62681159420289756, 0.34226190476191221}"
    },
    {
      "_class": "curvePoint",
      "cornerRadius": 0,
      "curveFrom": "{0.62681159420289756, 0.83482150297617908}",
      "curveMode": 4,
      "curveTo": "{0.62681159420289756, 0.81994047619048271}",
      "hasCurveFrom": true,
      "hasCurveTo": false,
      "point": "{0.62681159420289756, 0.81994047619048271}"
    },
    {
      "_class": "curvePoint",
      "cornerRadius": 0,
      "curveFrom": "{0.64190824275362357, 0.864583377976192}",
      "curveMode": 2,
      "curveTo": "{0.62983088768116602, 0.84672614583332673}",
      "hasCurveFrom": true,
      "hasCurveTo": true,
      "point": "{0.63586956521738192, 0.85565476190476986}"
    },
    {
      "_class": "curvePoint",
      "cornerRadius": 0,
      "curveFrom": "{0.68719815217391489, 0.8814484374999888}",
      "curveMode": 2,
      "curveTo": "{0.65338155797101283, 0.87152775297618412}",
      "hasCurveFrom": true,
      "hasCurveTo": true,
      "point": "{0.67028985507246386, 0.87648809523809701}"
    },
    {
      "_class": "curvePoint",
      "cornerRadius": 0,
      "curveFrom": "{0.77113541666666607, 0.88764881696428333}",
      "curveMode": 2,
      "curveTo": "{0.71074864130435222, 0.88467261160713562}",
      "hasCurveFrom": true,
      "hasCurveTo": true,
      "point": "{0.7409420289855092, 0.88616071428572007}"
    },
    {
      "_class": "curvePoint",
      "cornerRadius": 0,
      "curveFrom": "{0.85869565217390942, 0.88839285714285243}",
      "curveMode": 4,
      "curveTo": "{0.81038623188405312, 0.88839285714285243}",
      "hasCurveFrom": false,
      "hasCurveTo": true,
      "point": "{0.85869565217390942, 0.88839285714285243}"
    },
    {
      "_class": "curvePoint",
      "cornerRadius": 0,
      "curveFrom": "{1, 0.88839285714285243}",
      "curveMode": 1,
      "curveTo": "{1, 0.88839285714285243}",
      "hasCurveFrom": false,
      "hasCurveTo": false,
      "point": "{1, 0.88839285714285243}"
    },
    {
      "_class": "curvePoint",
      "cornerRadius": 0,
      "curveFrom": "{1, 1}",
      "curveMode": 1,
      "curveTo": "{1, 1}",
      "hasCurveFrom": false,
      "hasCurveTo": false,
      "point": "{1, 1}"
    },
    {
      "_class": "curvePoint",
      "cornerRadius": 0,
      "curveFrom": "{0.68478221014491214, 1}",
      "curveMode": 4,
      "curveTo": "{0.76449275362319946, 1}",
      "hasCurveFrom": true,
      "hasCurveTo": false,
      "point": "{0.76449275362319946, 1}"
    },
    {
      "_class": "curvePoint",
      "cornerRadius": 0,
      "curveFrom": "{0.5030190398550719, 0.98883926339284955}",
      "curveMode": 2,
      "curveTo": "{0.61654617753623553, 0.9977678794642928}",
      "hasCurveFrom": true,
      "hasCurveTo": true,
      "point": "{0.55978260869564089, 0.99330357142858172}"
    },
    {
      "_class": "curvePoint",
      "cornerRadius": 0,
      "curveFrom": "{0.38707711956521429, 0.95684517857142892}",
      "curveMode": 2,
      "curveTo": "{0.45712577898551493, 0.98065482142856852}",
      "hasCurveFrom": true,
      "hasCurveTo": true,
      "point": "{0.42210144927536458, 0.96874999999999867}"
    },
    {
      "_class": "curvePoint",
      "cornerRadius": 0,
      "curveFrom": "{0.32729460144926537, 0.89632925595237689}",
      "curveMode": 2,
      "curveTo": "{0.36111119565216732, 0.93998026785714694}",
      "hasCurveFrom": true,
      "hasCurveTo": true,
      "point": "{0.34420289855071634, 0.91815476190475143}"
    },
    {
      "_class": "curvePoint",
      "cornerRadius": 0,
      "curveFrom": "{0.31884057971014457, 0.83184523809523803}",
      "curveMode": 4,
      "curveTo": "{0.31884057971014457, 0.86755970238094748}",
      "hasCurveFrom": false,
      "hasCurveTo": true,
      "point": "{0.31884057971014457, 0.83184523809523803}"
    },
    {
      "_class": "curvePoint",
      "cornerRadius": 0,
      "curveFrom": "{0.31884057971014457, 0.34226190476191221}",
      "curveMode": 1,
      "curveTo": "{0.31884057971014457, 0.34226190476191221}",
      "hasCurveFrom": false,
      "hasCurveTo": false,
      "point": "{0.31884057971014457, 0.34226190476191221}"
    },
    {
      "_class": "curvePoint",
      "cornerRadius": 0,
      "curveFrom": "{0, 0.34226190476191221}",
      "curveMode": 1,
      "curveTo": "{0, 0.34226190476191221}",
      "hasCurveFrom": false,
      "hasCurveTo": false,
      "point": "{0, 0.34226190476191221}"
    },
    {
      "_class": "curvePoint",
      "cornerRadius": 0,
      "curveFrom": "{0, 0.23065476190476461}",
      "curveMode": 1,
      "curveTo": "{0, 0.23065476190476461}",
      "hasCurveFrom": false,
      "hasCurveTo": false,
      "point": "{0, 0.23065476190476461}"
    },
    {
      "_class": "curvePoint",
      "cornerRadius": 0,
      "curveFrom": "{0.31884057971014457, 0.23065476190476461}",
      "curveMode": 1,
      "curveTo": "{0.31884057971014457, 0.23065476190476461}",
      "hasCurveFrom": false,
      "hasCurveTo": false,
      "point": "{0.31884057971014457, 0.23065476190476461}"
    },
    {
      "_class": "curvePoint",
      "cornerRadius": 0,
      "curveFrom": "{0.31884057971014457, 0}",
      "curveMode": 1,
      "curveTo": "{0.31884057971014457, 0}",
      "hasCurveFrom": false,
      "hasCurveTo": false,
      "point": "{0.31884057971014457, 0}"
    },
    {
      "_class": "curvePoint",
      "cornerRadius": 0,
      "curveFrom": "{0.62681159420289756, 0}",
      "curveMode": 1,
      "curveTo": "{0.62681159420289756, 0}",
      "hasCurveFrom": false,
      "hasCurveTo": false,
      "point": "{0.62681159420289756, 0}"
    }
  ],
  "resizingConstraint": 63,
  "resizingType": 0,
  "rotation": 0,
  "shouldBreakMaskChain": false,
  "style": {
    "_class": "style",
    "blur": {
      "_class": "blur",
      "center": "{0.5, 0.5}",
      "isEnabled": false,
      "motionAngle": 0,
      "radius": 10,
      "saturation": 1,
      "type": 0
    },
    "borderOptions": {
      "_class": "borderOptions",
      "dashPattern": [
      ],
      "isEnabled": true,
      "lineCapStyle": 0,
      "lineJoinStyle": 0
    },
    "borders": [
    ],
    "colorControls": {
      "_class": "colorControls",
      "brightness": 0,
      "contrast": 1,
      "hue": 0,
      "isEnabled": true,
      "saturation": 1
    },
    "contextSettings": {
      "_class": "graphicsContextSettings",
      "blendMode": 0,
      "opacity": 1
    },
    "do_objectID": "E07FBADA-F4D6-4D06-9855-43A179966811",
    "endMarkerType": 0,
    "fills": [
    ],
    "innerShadows": [
    ],
    "miterLimit": 10,
    "shadows": [
    ],
    "startMarkerType": 0,
    "windingRule": 1
  }
}